KiticaClient/__init__.py
KiticaClient/kiticaclient.py
KiticaClient/version.py
KiticaClient/base/__init__.py
KiticaClient/base/base.py
KiticaClient/client/__init__.py
KiticaClient/client/adb.py
KiticaClient/client/ios.py
KiticaClient/common/__init__.py
KiticaClient/common/constants.py
KiticaClient/common/logger.py
kiticaclient-1.4a9.dist-info/LICENSE
kiticaclient-1.4a9.dist-info/METADATA
kiticaclient-1.4a9.dist-info/WHEEL
kiticaclient-1.4a9.dist-info/entry_points.txt
kiticaclient-1.4a9.dist-info/top_level.txt
kiticaclient-1.4a9.dist-info/RECORD
