Metadata-Version: 2.1
Name: kiticaclient
Version: 1.4a9
Summary: Kitica Devicepool Client.
Home-page: https://github.com/MainSystemDev/kitica
Author: Joshua Kim Rivera
Author-email: joshua.rivera@mnltechnology.com
License: MIT License
Platform: any
Classifier: Development Status :: 4 - Beta
Classifier: License :: OSI Approved :: MIT License
Classifier: Operating System :: OS Independent
Classifier: Programming Language :: Python :: 3
Classifier: Topic :: Software Development :: Testing
Requires-Dist: Appium-Python-Client
Requires-Dist: PyYAML
Requires-Dist: pure-python-adb (==0.2.3.dev0)
Requires-Dist: requests
